sc_mc_interface/__init__.py
sc_mc_interface/mc_conversation.py
sc_mc_interface/mc_message.py
sc_mc_interface/whatsapp_mode.py
sc_mc_interface-1.0.9.dist-info/METADATA
sc_mc_interface-1.0.9.dist-info/WHEEL
sc_mc_interface-1.0.9.dist-info/top_level.txt
sc_mc_interface-1.0.9.dist-info/RECORD
