Metadata-Version: 2.1
Name: sc_mc_interface
Version: 1.0.9
Summary: mc/Wa模版相关接口
Author: dyy
Requires-Dist: requests >=2.0.0
